case_insensitive_dict/__init__.py
case_insensitive_dict/case_insensitive_dict.py
case_insensitive_dict/utils.py
case_insensitive_dict-0.1.3.dist-info/DESCRIPTION.rst
case_insensitive_dict-0.1.3.dist-info/METADATA
case_insensitive_dict-0.1.3.dist-info/RECORD
case_insensitive_dict-0.1.3.dist-info/WHEEL
case_insensitive_dict-0.1.3.dist-info/metadata.json
case_insensitive_dict-0.1.3.dist-info/top_level.txt
