Metadata-Version: 2.0
Name: case-insensitive-dict
Version: 0.1.3
Summary: Case Insensitive Dict for python.
Home-page: UNKNOWN
Author: Stone Pagamentos
Author-email: devrc@stone.com.br
License: MIT
Keywords: case Insensitive dict
Platform: UNKNOWN
Classifier: Development Status :: 1 - Planning
Classifier: Programming Language :: Python
